windy/__init__.py
fcfc_windy-0.2.0.dist-info/METADATA
fcfc_windy-0.2.0.dist-info/WHEEL
fcfc_windy-0.2.0.dist-info/top_level.txt
fcfc_windy-0.2.0.dist-info/RECORD
