Metadata-Version: 2.1
Name: fcfc-windy
Version: 0.2.0
Summary: Windy
Home-page: UNKNOWN
Author: JingBh
Author-email: jingbohao@yeah.net
License: UNKNOWN
